bimcp_mcp/__init__.py
bimcp_mcp/client.py
bimcp_mcp-1.0.0.dist-info/METADATA
bimcp_mcp-1.0.0.dist-info/WHEEL
bimcp_mcp-1.0.0.dist-info/entry_points.txt
bimcp_mcp-1.0.0.dist-info/RECORD
