Metadata-Version: 2.4
Name: bimcp-mcp
Version: 1.0.0
Summary: Connect Claude Desktop to BIMCP Cloud Service for Revit integration
Project-URL: Homepage, https://bimcp.com
Project-URL: Documentation, https://docs.bimcp.com/mcp
Project-URL: API Keys, https://bimcp.com/api-keys
Author-email: BIMCP <support@bimcp.com>
License: MIT
Keywords: ai,bim,claude,mcp,model-context-protocol,revit
Classifier: Development Status :: 4 - Beta
Classifier: Intended Audience :: Developers
Classifier: License :: OSI Approved :: MIT License
Classifier: Programming Language :: Python :: 3
Classifier: Programming Language :: Python :: 3.8
Classifier: Programming Language :: Python :: 3.9
Classifier: Programming Language :: Python :: 3.10
Classifier: Programming Language :: Python :: 3.11
Classifier: Programming Language :: Python :: 3.12
Requires-Python: >=3.8
Requires-Dist: httpx>=0.25.0
Requires-Dist: mcp>=0.5.0
